calculator_wasik/__init__.py
calculator_wasik/core.py
calculator_wasik-0.1.0.dist-info/METADATA
calculator_wasik-0.1.0.dist-info/WHEEL
calculator_wasik-0.1.0.dist-info/top_level.txt
calculator_wasik-0.1.0.dist-info/RECORD
