Metadata-Version: 2.4
Name: calculator_wasik
Version: 0.1.0
Summary: A simple demo python package
Author-email: Wasik Ahmed Apon <aponwasikahmed@gmail.com>
License-Expression: MIT
Project-URL: Homepage, https://github.com/wasikahmed/mypackage
Project-URL: Documentation, https://mypackage/docs
Project-URL: Source, https://github.com/wasikahmed/mypackage
Requires-Python: >=3.10
Requires-Dist: requests>=2.0
